setup.py
Circle_Beacon.egg-info/PKG-INFO
Circle_Beacon.egg-info/SOURCES.txt
Circle_Beacon.egg-info/dependency_links.txt
Circle_Beacon.egg-info/entry_points.txt
Circle_Beacon.egg-info/requires.txt
Circle_Beacon.egg-info/top_level.txt
alert_circle/__init__.py