Metadata-Version: 1.0
Name: Circle-Beacon
Version: 2.0.0
Summary: ...
Home-page: https://github.com/migurski/circle-beacon
Author: Michal Migurski
Author-email: mike-github@teczno.com
License: UNKNOWN
Platform: UNKNOWN
